asterias/__init__.py
asterias/py.typed
asterias-0.0.1.dist-info/METADATA
asterias-0.0.1.dist-info/WHEEL
asterias-0.0.1.dist-info/licenses/LICENSE
asterias-0.0.1.dist-info/RECORD
